{
    "$id": "https://docs.cubecommons.ca/schemas/content/add_content_request.json",
    "$schema": "https://json-schema.org/draft/2020-12/schema",
    "title": "Add Content",
    "description": "Adds Content",
    "type": "object",
    "properties": {
        "profileId": {
            "type": "string"
        },
        "type": {
            "type": "string"
        },
        "title": {
            "type": "string"
        },
        "expiry": {
            "type": "string"
        },
        "description": {
            "type": "string"
        },
        "coverImageFileId": {
            "type": "string"
        },
        "mediaFileId": {
            "type": "string"
        },
        "subtitlesFileId": {
            "type": "string"
        },
        "transcriptFileId": {
            "type": "string"
        },
        "coverImageText": {
            "type": "string"
        },
        "collaborators": {
            "type": "array",
            "items": {
                "type": "string"
            }
        },
        "contributors": {
            "type": "array",
            "items": {
                "type": "string"
            }
        },
        "tags": {
            "type": "array",
            "items": {
                "type": "string"
            }
        }
    },
    "required": [
        "profileId",
        "type",
        "title",
        "expiry",
        "description",
        "coverImageFileId",
        "mediaFileId",
        "coverImageText",
        "collaborators",
        "contributors"
    ]
}
