{
  "meta": {
    "offset": 0,
    "limit": 1,
    "total": 1
  },
  "data": [
    {
      "profileId": "7b20d847-d928-4726-98dd-bab4bfcf8ccf",
      "type": "video",
      "category": "video",
      "title": "Test Video Upload",
      "expiry": "Say What??? Why should this ever be over?",
      "description": "This text field shall describe the content file.",
      "coverImageFileId": "24d6b370-a709-4a7b-b323-752186cd492d",
      "mediaFileId": "7b20d847-d928-4726-98dd-bab4bfcf8ccf",
      "vttFileId": "6f05411a-e991-4346-be54-6dc2b4e4e528",
      "coverImageText": "Thumbnail Text",
      "contributors": {
        "artist": ["artist"],
        "camera": ["camera person"]
      },
      "collaborators": [
        "ac56cff2-553e-4f7f-94ea-c703c1c0dce6",
        "ac56cff2-553e-4f7f-94ea-c703c1c0dce6"
      ],
      "tags": ["integration testing", "tags are hard"]
    }
  ]
}
